PLinterafit/__init__.py
PLinterafit/analysis.py
PLinterafit/dataPreparation.py
PLinterafit/fitting.py
PLinterafit/models.py
PLinterafit/plotting.py
PLinterafit/statistics.py
PLinterafit-0.0.2.dist-info/LICENSE.txt
PLinterafit-0.0.2.dist-info/METADATA
PLinterafit-0.0.2.dist-info/WHEEL
PLinterafit-0.0.2.dist-info/top_level.txt
PLinterafit-0.0.2.dist-info/RECORD
