Metadata-Version: 2.1
Name: PLinterafit
Version: 0.0.2
Summary: This is a package for Voigt fitting of a photolumiscence spectrum and statistically evaluating the fitting results.
Home-page: https://github.com/pypa/sampleproject
Author: Viktor Bender, Bayarjargal N.Tugchin
Author-email: vbender@physik.hu-berlin.de, n.bayarjargal@uni-jena.de
License: UNKNOWN
Keywords: PL spectra fitting
Platform: UNKNOWN
Classifier: Programming Language :: Python :: 3
Classifier: License :: OSI Approved :: MIT License
Classifier: Operating System :: OS Independent
Requires-Python: >=3.6
